pyramid_zipkin/__init__.py
pyramid_zipkin/py.typed
pyramid_zipkin/request_helper.py
pyramid_zipkin/tween.py
pyramid_zipkin/version.py
pyramid_zipkin/zipkin.py
pyramid_zipkin-3.0.1.dist-info/LICENSE.txt
pyramid_zipkin-3.0.1.dist-info/METADATA
pyramid_zipkin-3.0.1.dist-info/WHEEL
pyramid_zipkin-3.0.1.dist-info/top_level.txt
pyramid_zipkin-3.0.1.dist-info/RECORD
