Metadata-Version: 2.1
Name: pyramid-zipkin
Version: 3.0.1
Summary: Zipkin instrumentation for the Pyramid framework.
Home-page: https://github.com/Yelp/pyramid_zipkin
Author: Yelp, Inc.
Author-email: opensource+pyramid-zipkin@yelp.com
License: Copyright Yelp 2018
Platform: UNKNOWN
Classifier: Development Status :: 5 - Production/Stable
Classifier: Intended Audience :: Developers
Classifier: Topic :: Software Development :: Libraries :: Python Modules
Classifier: License :: OSI Approved :: Apache Software License
Classifier: Operating System :: OS Independent
Classifier: Programming Language :: Python :: 3.8
Provides: pyramid_zipkin
Requires-Python: >=3.8
Requires-Dist: py-zipkin>=0.18.1
Requires-Dist: pyramid
